[
    {
    "name": "Alley",
    "author": "NB Design",
    "url": "https://github.com/NewBDesign/SYNTH/blob/main/wallpapers/phone/Alley.png?raw=true",
    "collections": "Phone",
    "downloadable": true,
    "dimensions": "1024x1816"
    },
    {
    "name": "Beach",
    "author": "NB Design",
    "url": "https://github.com/NewBDesign/SYNTH/blob/main/wallpapers/phone/Beach.png?raw=true",
    "collections": "Phone",
    "downloadable": true,
    "dimensions": "1024x1816"
    },
    {
    "name": "Bike",
    "author": "NB Design",
    "url": "https://github.com/NewBDesign/SYNTH/blob/main/wallpapers/phone/Bike.png?raw=true",
    "collections": "Phone",
    "downloadable": true,
    "dimensions": "1024x1816"
    },
    {
    "name": "Bridge",
    "author": "NB Design",
    "url": "https://github.com/NewBDesign/SYNTH/blob/main/wallpapers/phone/Bridge.png?raw=true",
    "collections": "Phone",
    "downloadable": true,
    "dimensions": "1024x1816"
    },
    {
    "name": "Castle",
    "author": "NB Design",
    "url": "https://github.com/NewBDesign/SYNTH/blob/main/wallpapers/phone/Castle.png?raw=true",
    "collections": "Phone",
    "downloadable": true,
    "dimensions": "1024x1816"
    },
    {
    "name": "City",
    "author": "NB Design",
    "url": "https://github.com/NewBDesign/SYNTH/blob/main/wallpapers/phone/City.png?raw=true",
    "collections": "Phone",
    "downloadable": true,
    "dimensions": "1024x1816"
    },
    {
    "name": "District",
    "author": "NB Design",
    "url": "https://github.com/NewBDesign/SYNTH/blob/main/wallpapers/phone/District.png?raw=true",
    "collections": "Phone",
    "downloadable": true,
    "dimensions": "1024x1816"
    },
    {
    "name": "Dusk",
    "author": "NB Design",
    "url": "https://github.com/NewBDesign/SYNTH/blob/main/wallpapers/phone/Dusk.png?raw=true",
    "collections": "Phone",
    "downloadable": true,
    "dimensions": "1024x1816"
    },
    {
    "name": "Electronic",
    "author": "NB Design",
    "url": "https://github.com/NewBDesign/SYNTH/blob/main/wallpapers/phone/Electronic.png?raw=true",
    "collections": "Phone",
    "downloadable": true,
    "dimensions": "1024x1816"
    },
    {
    "name": "Gorge",
    "author": "NB Design",
    "url": "https://github.com/NewBDesign/SYNTH/blob/main/wallpapers/phone/Gorge.png?raw=true",
    "collections": "Phone",
    "downloadable": true,
    "dimensions": "1024x1816"
    },
    {
    "name": "Jungle",
    "author": "NB Design",
    "url": "https://github.com/NewBDesign/SYNTH/blob/main/wallpapers/phone/Jungle.png?raw=true",
    "collections": "Phone",
    "downloadable": true,
    "dimensions": "1024x1816"
    },
    {
    "name": "Landscape",
    "author": "NB Design",
    "url": "https://github.com/NewBDesign/SYNTH/blob/main/wallpapers/phone/Landscape.png?raw=true",
    "collections": "Phone",
    "downloadable": true,
    "dimensions": "1024x1816"
    },
    {
    "name": "Laser",
    "author": "NB Design",
    "url": "https://github.com/NewBDesign/SYNTH/blob/main/wallpapers/phone/Laser.png?raw=true",
    "collections": "Phone",
    "downloadable": true,
    "dimensions": "1024x1816"
    },
    {
    "name": "Mega",
    "author": "NB Design",
    "url": "https://github.com/NewBDesign/SYNTH/blob/main/wallpapers/phone/Mega.png?raw=true",
    "collections": "Phone",
    "downloadable": true,
    "dimensions": "1024x1816"
    },
    {
    "name": "Orbit",
    "author": "NB Design",
    "url": "https://github.com/NewBDesign/SYNTH/blob/main/wallpapers/phone/Orbit.png?raw=true",
    "collections": "Phone",
    "downloadable": true,
    "dimensions": "1024x1816"
    },
    {
    "name": "Pink",
    "author": "NB Design",
    "url": "https://github.com/NewBDesign/SYNTH/blob/main/wallpapers/phone/Pink.png?raw=true",
    "collections": "Phone",
    "downloadable": true,
    "dimensions": "1024x1816"
    },
    {
    "name": "Plants",
    "author": "NB Design",
    "url": "https://github.com/NewBDesign/SYNTH/blob/main/wallpapers/phone/Plants.png?raw=true",
    "collections": "Phone",
    "downloadable": true,
    "dimensions": "1024x1816"
    },
    {
    "name": "Rain",
    "author": "NB Design",
    "url": "https://github.com/NewBDesign/SYNTH/blob/main/wallpapers/phone/Rain.png?raw=true",
    "collections": "Phone",
    "downloadable": true,
    "dimensions": "1024x1816"
    },
    {
    "name": "Sea",
    "author": "NB Design",
    "url": "https://github.com/NewBDesign/SYNTH/blob/main/wallpapers/phone/Sea.png?raw=true",
    "collections": "Phone",
    "downloadable": true,
    "dimensions": "1024x1816"
    },
    {
    "name": "Skyscrapers",
    "author": "NB Design",
    "url": "https://github.com/NewBDesign/SYNTH/blob/main/wallpapers/phone/Skyscrapers.png?raw=true",
    "collections": "Phone",
    "downloadable": true,
    "dimensions": "1024x1816"
    },
    {
    "name": "Slum",
    "author": "NB Design",
    "url": "https://github.com/NewBDesign/SYNTH/blob/main/wallpapers/phone/Slum.png?raw=true",
    "collections": "Phone",
    "downloadable": true,
    "dimensions": "1024x1816"
    },
    {
    "name": "Surfing",
    "author": "NB Design",
    "url": "https://github.com/NewBDesign/SYNTH/blob/main/wallpapers/phone/Surfing.png?raw=true",
    "collections": "Phone",
    "downloadable": true,
    "dimensions": "1024x1816"
    },
    {
    "name": "Taxi",
    "author": "NB Design",
    "url": "https://github.com/NewBDesign/SYNTH/blob/main/wallpapers/phone/Taxi.png?raw=true",
    "collections": "Phone",
    "downloadable": true,
    "dimensions": "1024x1816"
    },
    {
    "name": "Traffic",
    "author": "NB Design",
    "url": "https://github.com/NewBDesign/SYNTH/blob/main/wallpapers/phone/Traffic.png?raw=true",
    "collections": "Phone",
    "downloadable": true,
    "dimensions": "1024x1816"
    },
    {
    "name": "Waves",
    "author": "NB Design",
    "url": "https://github.com/NewBDesign/SYNTH/blob/main/wallpapers/phone/Waves.png?raw=true",
    "collections": "Phone",
    "downloadable": true,
    "dimensions": "1024x1816"
    },
    {
    "name": "Abstract",
    "author": "NB Design",
    "url": "https://github.com/NewBDesign/SYNTH/blob/main/wallpapers/tablet/Abstract.png?raw=true",
    "collections": "Tablet",
    "downloadable": true,
    "dimensions": "1816x1024"
    },
    {
    "name": "Acryl",
    "author": "NB Design",
    "url": "https://github.com/NewBDesign/SYNTH/blob/main/wallpapers/tablet/Acryl.png?raw=true",
    "collections": "Tablet",
    "downloadable": true,
    "dimensions": "1816x1024"
    },
    {
    "name": "Aurora",
    "author": "NB Design",
    "url": "https://github.com/NewBDesign/SYNTH/blob/main/wallpapers/tablet/Aurora.png?raw=true",
    "collections": "Tablet",
    "downloadable": true,
    "dimensions": "1816x1024"
    },
    {
    "name": "Blue",
    "author": "NB Design",
    "url": "https://github.com/NewBDesign/SYNTH/blob/main/wallpapers/tablet/Blue.png?raw=true",
    "collections": "Tablet",
    "downloadable": true,
    "dimensions": "1816x1024"
    },
    {
    "name": "Car",
    "author": "NB Design",
    "url": "https://github.com/NewBDesign/SYNTH/blob/main/wallpapers/tablet/Car.png?raw=true",
    "collections": "Tablet",
    "downloadable": true,
    "dimensions": "1816x1024"
    },
    {
    "name": "Cubes",
    "author": "NB Design",
    "url": "https://github.com/NewBDesign/SYNTH/blob/main/wallpapers/tablet/Cubes.png?raw=true",
    "collections": "Tablet",
    "downloadable": true,
    "dimensions": "1816x1024"
    },
    {
    "name": "Desert",
    "author": "NB Design",
    "url": "https://github.com/NewBDesign/SYNTH/blob/main/wallpapers/tablet/Desert.png?raw=true",
    "collections": "Tablet",
    "downloadable": true,
    "dimensions": "1816x1024"
    },
    {
    "name": "Driving",
    "author": "NB Design",
    "url": "https://github.com/NewBDesign/SYNTH/blob/main/wallpapers/tablet/Driving.png?raw=true",
    "collections": "Tablet",
    "downloadable": true,
    "dimensions": "1816x1024"
    },
    {
    "name": "Galaxy",
    "author": "NB Design",
    "url": "https://github.com/NewBDesign/SYNTH/blob/main/wallpapers/tablet/Galaxy.png?raw=true",
    "collections": "Tablet",
    "downloadable": true,
    "dimensions": "1816x1024"
    },
    {
    "name": "Island",
    "author": "NB Design",
    "url": "https://github.com/NewBDesign/SYNTH/blob/main/wallpapers/tablet/Island.png?raw=true",
    "collections": "Tablet",
    "downloadable": true,
    "dimensions": "1816x1024"
    },
    {
    "name": "Lights",
    "author": "NB Design",
    "url": "https://github.com/NewBDesign/SYNTH/blob/main/wallpapers/tablet/Lights.png?raw=true",
    "collections": "Tablet",
    "downloadable": true,
    "dimensions": "1816x1024"
    },
    {
    "name": "Metro",
    "author": "NB Design",
    "url": "https://github.com/NewBDesign/SYNTH/blob/main/wallpapers/tablet/Metro.png?raw=true",
    "collections": "Tablet",
    "downloadable": true,
    "dimensions": "1816x1024"
    },
    {
    "name": "Mountains",
    "author": "NB Design",
    "url": "https://github.com/NewBDesign/SYNTH/blob/main/wallpapers/tablet/Mountains.png?raw=true",
    "collections": "Tablet",
    "downloadable": true,
    "dimensions": "1816x1024"
    },
    {
    "name": "Nebula",
    "author": "NB Design",
    "url": "https://github.com/NewBDesign/SYNTH/blob/main/wallpapers/tablet/Nebula.png?raw=true",
    "collections": "Tablet",
    "downloadable": true,
    "dimensions": "1816x1024"
    },
    {
    "name": "Ocean",
    "author": "NB Design",
    "url": "https://github.com/NewBDesign/SYNTH/blob/main/wallpapers/tablet/Ocean.png?raw=true",
    "collections": "Tablet",
    "downloadable": true,
    "dimensions": "1816x1024"
    },
    {
    "name": "Pattern",
    "author": "NB Design",
    "url": "https://github.com/NewBDesign/SYNTH/blob/main/wallpapers/tablet/Pattern.png?raw=true",
    "collections": "Tablet",
    "downloadable": true,
    "dimensions": "1816x1024"
    },
    {
    "name": "Planets",
    "author": "NB Design",
    "url": "https://github.com/NewBDesign/SYNTH/blob/main/wallpapers/tablet/Planets.png?raw=true",
    "collections": "Tablet",
    "downloadable": true,
    "dimensions": "1816x1024"
    },
    {
    "name": "Purple",
    "author": "NB Design",
    "url": "https://github.com/NewBDesign/SYNTH/blob/main/wallpapers/tablet/Purple.png?raw=true",
    "collections": "Tablet",
    "downloadable": true,
    "dimensions": "1816x1024"
    },
    {
    "name": "Ruins",
    "author": "NB Design",
    "url": "https://github.com/NewBDesign/SYNTH/blob/main/wallpapers/tablet/Ruins.png?raw=true",
    "collections": "Tablet",
    "downloadable": true,
    "dimensions": "1816x1024"
    },
    {
    "name": "Safari",
    "author": "NB Design",
    "url": "https://github.com/NewBDesign/SYNTH/blob/main/wallpapers/tablet/Safari.png?raw=true",
    "collections": "Tablet",
    "downloadable": true,
    "dimensions": "1816x1024"
    },
    {
    "name": "Skyline",
    "author": "NB Design",
    "url": "https://github.com/NewBDesign/SYNTH/blob/main/wallpapers/tablet/Skyline.png?raw=true",
    "collections": "Tablet",
    "downloadable": true,
    "dimensions": "1816x1024"
    },
    {
    "name": "Smooth",
    "author": "NB Design",
    "url": "https://github.com/NewBDesign/SYNTH/blob/main/wallpapers/tablet/Smooth.png?raw=true",
    "collections": "Tablet",
    "downloadable": true,
    "dimensions": "1816x1024"
    },
    {
    "name": "Storm",
    "author": "NB Design",
    "url": "https://github.com/NewBDesign/SYNTH/blob/main/wallpapers/tablet/Storm.png?raw=true",
    "collections": "Tablet",
    "downloadable": true,
    "dimensions": "1816x1024"
    },
    {
    "name": "Sunset",
    "author": "NB Design",
    "url": "https://github.com/NewBDesign/SYNTH/blob/main/wallpapers/tablet/Sunset.png?raw=true",
    "collections": "Tablet",
    "downloadable": true,
    "dimensions": "1816x1024"
    },
    {
    "name": "Wasteland",
    "author": "NB Design",
    "url": "https://github.com/NewBDesign/SYNTH/blob/main/wallpapers/tablet/Wasteland.png?raw=true",
    "collections": "Tablet",
    "downloadable": true,
    "dimensions": "1816x1024"
    }
]
